pmdatapipelines/__init__.py
pmdatapipelines/pmaws.py
pmdatapipelines/pmcore.py
pmdatapipelines/pmmatillion.py
pmdatapipelines/pmtransfer.py
pmdatapipelines/pmtransfer_light.py
pmdatapipelines/pmtransform.py
pmdatapipelines-0.0.47.dist-info/LICENSE
pmdatapipelines-0.0.47.dist-info/METADATA
pmdatapipelines-0.0.47.dist-info/WHEEL
pmdatapipelines-0.0.47.dist-info/top_level.txt
pmdatapipelines-0.0.47.dist-info/RECORD
