Metadata-Version: 2.1
Name: pmdatapipelines
Version: 0.0.47
Summary: Data pipeline library for Polaris Media
Home-page: UNKNOWN
Author: Jørgen Frøland
Author-email: jorgen.froland@polarismedia.no
License: UNKNOWN
Platform: UNKNOWN
Classifier: Programming Language :: Python :: 3
Classifier: License :: OSI Approved :: MIT License
Classifier: Operating System :: OS Independent
Requires-Dist: boto3
Requires-Dist: pandas
Requires-Dist: pyarrow
